LICENSE
MANIFEST.in
README.md
setup.py
tap_impact/__init__.py
tap_impact/client.py
tap_impact/discover.py
tap_impact/schema.py
tap_impact/streams.py
tap_impact/sync.py
tap_impact/transform.py
tap_impact.egg-info/PKG-INFO
tap_impact.egg-info/SOURCES.txt
tap_impact.egg-info/dependency_links.txt
tap_impact.egg-info/entry_points.txt
tap_impact.egg-info/requires.txt
tap_impact.egg-info/top_level.txt
tap_impact/schemas/action_inquiries.json
tap_impact/schemas/action_updates.json
tap_impact/schemas/actions.json
tap_impact/schemas/ads.json
tap_impact/schemas/api_submissions.json
tap_impact/schemas/campaigns.json
tap_impact/schemas/catalog_items.json
tap_impact/schemas/catalogs.json
tap_impact/schemas/company_information.json
tap_impact/schemas/contacts.json
tap_impact/schemas/conversion_paths.json
tap_impact/schemas/deals.json
tap_impact/schemas/exception_list_items.json
tap_impact/schemas/exception_lists.json
tap_impact/schemas/ftp_file_submissions.json
tap_impact/schemas/invoices.json
tap_impact/schemas/media_partner_groups.json
tap_impact/schemas/media_partners.json
tap_impact/schemas/notes.json
tap_impact/schemas/phone_numbers.json
tap_impact/schemas/promo_codes.json
tap_impact/schemas/report_metadata.json
tap_impact/schemas/reports.json
tap_impact/schemas/tracking_value_requests.json
tap_impact/schemas/unique_urls.json