Metadata-Version: 2.1
Name: tap-impact
Version: 2.1.0
Summary: Singer.io tap for extracting data from the Impact Advertiser, Partner, Agency APIs
Author: jeff.huth@bytecode.io
Classifier: Programming Language :: Python :: 3 :: Only
License-File: LICENSE
Requires-Dist: backoff==1.8.0
Requires-Dist: requests==2.32.3
Requires-Dist: singer-python==5.8.1
Provides-Extra: dev
Requires-Dist: ipdb; extra == "dev"
Requires-Dist: pylint==2.5.3; extra == "dev"
